csharp_analyzer/__init__.py
csharp_analyzer/attribute.py
csharp_analyzer/class_.py
csharp_analyzer/file.py
csharp_analyzer/method.py
csharp_analyzer/namespace.py
csharp_analyzer/property.py
csharp_analyzer-0.2.5.dist-info/LICENCE
csharp_analyzer-0.2.5.dist-info/METADATA
csharp_analyzer-0.2.5.dist-info/WHEEL
csharp_analyzer-0.2.5.dist-info/top_level.txt
csharp_analyzer-0.2.5.dist-info/RECORD
